tinytok/__init__.py
tinytok/core.py
tinytok-0.4.8.dist-info/METADATA
tinytok-0.4.8.dist-info/WHEEL
tinytok-0.4.8.dist-info/top_level.txt
tinytok-0.4.8.dist-info/RECORD
