Metadata-Version: 2.4
Name: tinytok
Version: 0.4.8
Summary: Utility functions for processing TinyStories dataset by Eldan & Li
Home-page: https://github.com/vxnuaj/tinytok
Author: vxnuaj
Classifier: Programming Language :: Python :: 3
Classifier: Operating System :: OS Independent
Requires-Python: >=3.10
Requires-Dist: torch
Requires-Dist: pandas
Requires-Dist: tqdm
Requires-Dist: tokenizers
Requires-Dist: pyarrow
Requires-Dist: rich
Dynamic: author
Dynamic: classifier
Dynamic: description
Dynamic: description-content-type
Dynamic: home-page
Dynamic: requires-dist
Dynamic: requires-python
Dynamic: summary
